opyf/Analyzer.py
opyf/Files.py
opyf/Filters.py
opyf/Interpolate.py
opyf/MeshesAndTime.py
opyf/Render.py
opyf/Tools.py
opyf/Track.py
opyf/__init__.py
opyf/custom_cmap.py
opyf-1.7.dist-info/LICENSE
opyf-1.7.dist-info/METADATA
opyf-1.7.dist-info/WHEEL
opyf-1.7.dist-info/top_level.txt
opyf-1.7.dist-info/RECORD
