Metadata-Version: 2.1
Name: opyf
Version: 1.7
Summary: OpyFlow - Python package for Optical Flow measurements.
Author-email: Gauthier Rousseau <gauthier.rousseau@gmail.com>
Project-URL: Homepage, https://github.com/groussea/opyflow
Project-URL: Bug Tracker, https://github.com/groussea/opyflow/issues
Classifier: Development Status :: 4 - Beta
Classifier: Intended Audience :: Science/Research
Classifier: Topic :: Software Development :: Libraries :: Python Modules
Classifier: License :: OSI Approved :: GNU General Public License v3 (GPLv3)
Classifier: Programming Language :: Python :: 3
Requires-Python: >=3.7
License-File: LICENSE
Requires-Dist: ipython >7.0.0
Requires-Dist: vtk >9.0.0
Requires-Dist: opencv-python >4.0.0
Requires-Dist: tqdm >4.0
Requires-Dist: h5py >3.0.0
Requires-Dist: matplotlib >3.0.0
Requires-Dist: scipy >1.9.0
Requires-Dist: PyQt6 >6.0.0
